AUTHORS.rst
CHANGELOG.rst
LICENSE
MANIFEST.in
README.rst
convert_to_geodb_ubuntu.sh
setup.py
jmbo/__init__.py
jmbo/admin.py
jmbo/apps.py
jmbo/forms.py
jmbo/managers.py
jmbo/models.py
jmbo/monkey.py
jmbo/signals.py
jmbo/tasks.py
jmbo/urls.py
jmbo/utils.py
jmbo/views.py
jmbo.egg-info/PKG-INFO
jmbo.egg-info/SOURCES.txt
jmbo.egg-info/dependency_links.txt
jmbo.egg-info/not-zip-safe
jmbo.egg-info/requires.txt
jmbo.egg-info/top_level.txt
jmbo/api/__init__.py
jmbo/fixtures/photosizes.json
jmbo/locale/af/LC_MESSAGES/django.mo
jmbo/locale/af/LC_MESSAGES/django.po
jmbo/locale/fr/LC_MESSAGES/django.mo
jmbo/locale/fr/LC_MESSAGES/django.po
jmbo/management/__init__.py
jmbo/management/commands/__init__.py
jmbo/management/commands/jmbo_publish.py
jmbo/management/commands/load_photosizes.py
jmbo/management/commands/upgrade_to_geo.py
jmbo/migrations/0001_initial.py
jmbo/migrations/0001_initial.pyc
jmbo/migrations/0002_auto_20160530_1338.py
jmbo/migrations/0002_auto_20160530_1338.pyc
jmbo/migrations/0003_auto_20160530_1247.py
jmbo/migrations/0003_auto_20160530_1247.pyc
jmbo/migrations/0004_photosize_name_length.py
jmbo/migrations/0005_modelbase_layers.py
jmbo/migrations/0006_auto_20170206_1337.py
jmbo/migrations/0007_auto_20170314_1546.py
jmbo/migrations/0008_auto_20171124_1112.py
jmbo/migrations/__init__.py
jmbo/migrations/__init__.pyc
jmbo/static/jmbo/.DS_Store
jmbo/static/jmbo/css/.DS_Store
jmbo/static/jmbo/css/adv.css
jmbo/static/jmbo/css/_notes/dwsync.xml
jmbo/static/jmbo/images/clear.gif
jmbo/static/jmbo/images/facebook_share.png
jmbo/static/jmbo/images/google_share.png
jmbo/static/jmbo/images/twitter_share.png
jmbo/static/jmbo/js/custom.js
jmbo/static/jmbo/js/jquery-1.5.1.min.js
jmbo/static/jmbo/js/jquery.validate.min.js
jmbo/static/jmbo/js/_notes/dwsync.xml
jmbo/static/jmbo/pics/.DS_Store
jmbo/static/jmbo/pics/0330-rihanna-rolling-stone-00-480x648.jpg
jmbo/static/jmbo/pics/accept.png
jmbo/static/jmbo/pics/apple-touch-icon.png
jmbo/static/jmbo/pics/article-pic.jpg
jmbo/static/jmbo/pics/close.png
jmbo/static/jmbo/pics/comments.png
jmbo/static/jmbo/pics/exclamation.png
jmbo/static/jmbo/pics/favicon.gif
jmbo/static/jmbo/pics/favicon.ico
