Metadata-Version: 1.1
Name: jmbo
Version: 3.0.5
Summary: The Jmbo base product introduces a content type and various tools required to build Jmbo products.
Home-page: http://www.jmbo.org
Author: Praekelt Consulting
Author-email: dev@praekelt.com
License: BSD
Platform: UNKNOWN
Classifier: Programming Language :: Python
Classifier: License :: OSI Approved :: BSD License
Classifier: Development Status :: 5 - Production/Stable
Classifier: Operating System :: OS Independent
Classifier: Framework :: Django
Classifier: Intended Audience :: Developers
Classifier: Topic :: Internet :: WWW/HTTP :: Dynamic Content
